{"cameraMode":{"drawMode":0,"name":"Shaded","section":"Shading Mode"},"sceneLighting":true,"audioPlay":false,"sceneViewState":{"m_AlwaysRefresh":false,"showFog":true,"showSkybox":true,"showFlares":true,"showImageEffects":true,"showParticleSystems":true,"showVisualEffectGraphs":true,"m_FxEnabled":true},"in2DMode":false,"pivot":{"x":-3.8232672214508058,"y":4.226860523223877,"z":5.914284706115723},"rotation":{"x":-0.2800564765930176,"y":-0.7059544920921326,"z":0.37092915177345278,"w":-0.5347051024436951},"size":8.42884349822998,"orthographic":false}